evadevice/__init__.py
evadevice/eva_device.py
evadevice/airtest_plus/__init__.py
evadevice/airtest_plus/android.py
evadevice/airtest_plus/template_online.py
evadevice/base/__init__.py
evadevice/base/api.py
evadevice/ocr/__init__.py
evadevice/ocr/api.py
evadevice/ocr/model/__init__.py
evadevice/ocr/model/ppocr_keys_v1.txt
evadevice/ocr/model/ppocr_v3.py
evadevice/ocr/model/__pycache__/__init__.cpython-310.pyc
evadevice/ocr/model/__pycache__/ppocr_v3.cpython-310.pyc
evadevice/ocr/model/ch_PP-OCRv3_det_infer/inference.pdiparams
evadevice/ocr/model/ch_PP-OCRv3_det_infer/inference.pdiparams.info
evadevice/ocr/model/ch_PP-OCRv3_det_infer/inference.pdmodel
evadevice/ocr/model/ch_PP-OCRv3_rec_infer/inference.pdiparams
evadevice/ocr/model/ch_PP-OCRv3_rec_infer/inference.pdiparams.info
evadevice/ocr/model/ch_PP-OCRv3_rec_infer/inference.pdmodel
evadevice/ocr/model/ch_ppocr_mobile_v2.0_cls_infer/inference.pdiparams
evadevice/ocr/model/ch_ppocr_mobile_v2.0_cls_infer/inference.pdiparams.info
evadevice/ocr/model/ch_ppocr_mobile_v2.0_cls_infer/inference.pdmodel
evadevice/utils/__init__.py
evadevice/utils/logger.py
evadevice/utils/wrapper.py
evadevice/weautomator/__init__.py
evadevice/weautomator/api.py
evadevice/weautomator/param.py
evadevice-0.1.2.dist-info/LICENSE
evadevice-0.1.2.dist-info/METADATA
evadevice-0.1.2.dist-info/WHEEL
evadevice-0.1.2.dist-info/top_level.txt
evadevice-0.1.2.dist-info/RECORD
