Metadata-Version: 2.1
Name: evadevice
Version: 0.1.2
Summary: Automated Testing Tools for Android and iOS.
Home-page: https://github.com/shizhao-git/evadevice
Author: shizhao
Author-email: shizhao@mail.nwpu.edu.cn
License: UNKNOWN
Keywords: automation,automated-test,game,android,ios,windows,linux,macos
Platform: UNKNOWN
License-File: LICENSE
Requires-Dist: adbutils
Requires-Dist: tidevice
Requires-Dist: evatidevice
Requires-Dist: uiautomator2
Requires-Dist: airtest
